soga_video/cli.py
soga_video/config.py
soga_video/generator.py
soga_video-0.1.0.dist-info/METADATA
soga_video-0.1.0.dist-info/WHEEL
soga_video-0.1.0.dist-info/entry_points.txt
soga_video-0.1.0.dist-info/top_level.txt
soga_video-0.1.0.dist-info/RECORD
